README.md
untrack.py
untrack-0.0.1.dist-info/DESCRIPTION.rst
untrack-0.0.1.dist-info/METADATA
untrack-0.0.1.dist-info/RECORD
untrack-0.0.1.dist-info/WHEEL
untrack-0.0.1.dist-info/entry_points.txt
untrack-0.0.1.dist-info/metadata.json
untrack-0.0.1.dist-info/top_level.txt
untrack.egg-info/PKG-INFO
untrack.egg-info/SOURCES.txt
untrack.egg-info/dependency_links.txt
untrack.egg-info/entry_points.txt
untrack.egg-info/requires.txt
untrack.egg-info/top_level.txt
