Metadata-Version: 2.0
Name: untrack
Version: 0.0.1
Summary: A cmd wrapper to untrack file of git
Home-page: https://github.com/minghu6/untrack.git
Author: minghu6
Author-email: a19678zy@163.com
License: BSD License
Platform: UNKNOWN
Classifier: Intended Audience :: Developers
Classifier: License :: OSI Approved :: BSD License
Classifier: Operating System :: POSIX
Classifier: Programming Language :: Python
Classifier: Programming Language :: Python :: 3
Requires-Dist: color-print (==0.0.2)
Requires-Dist: docopt
Requires-Dist: sh
